grtoolkit/Combinatronics.py
grtoolkit/Datetime.py
grtoolkit/Decorators.py
grtoolkit/Economics.py
grtoolkit/File.py
grtoolkit/Format.py
grtoolkit/GUI.py
grtoolkit/Hardcode.py
grtoolkit/Heat.py
grtoolkit/InLine.py
grtoolkit/Kinematics.py
grtoolkit/MSAccess.py
grtoolkit/PDF.py
grtoolkit/PMP.py
grtoolkit/PYPI.py
grtoolkit/PowerPoint.py
grtoolkit/Python.py
grtoolkit/Quotes.py
grtoolkit/Reference.py
grtoolkit/SQLite.py
grtoolkit/Storage.py
grtoolkit/Threading.py
grtoolkit/VirtualEnv.py
grtoolkit/Visualization.py
grtoolkit/WebScraping.py
grtoolkit/Windows.py
grtoolkit/__init__.py
grtoolkit/Circuits/__init__.py
grtoolkit/Circuits/AC/__init__.py
grtoolkit/Circuits/Capacitors/__init__.py
grtoolkit/Circuits/Conductance/__init__.py
grtoolkit/Circuits/Filters/__init__.py
grtoolkit/Circuits/Inductors/__init__.py
grtoolkit/Circuits/OpAmps/__init__.py
grtoolkit/Circuits/RC/__init__.py
grtoolkit/Circuits/RL/__init__.py
grtoolkit/Circuits/Resistors/__init__.py
grtoolkit/Circuits/Transformations/__init__.py
grtoolkit/Circuits/Transistors/__init__.py
grtoolkit/Electromagnetism/__init__.py
grtoolkit/Fluids/__init__.py
grtoolkit/Math/__init__.py
grtoolkit/Math/sympyInterface/__init__.py
grtoolkit/Mechanics/CircularMotion.py
grtoolkit/Mechanics/Collisions.py
grtoolkit/Mechanics/Gravitation.py
grtoolkit/Mechanics/Kinematics.py
grtoolkit/Mechanics/ProjectileMotion.py
grtoolkit/Mechanics/Pulleys.py
grtoolkit/Mechanics/__init__.py
grtoolkit/Mechanics/Friction/__init__.py
grtoolkit/TTS/__init__.py
grtoolkit-20.11.4.data/scripts/generateBATlauncher.py
grtoolkit-20.11.4.data/scripts/generateQuotes.py
grtoolkit-20.11.4.data/scripts/generateQuotesPPT.py
grtoolkit-20.11.4.data/scripts/joinPDF.py
grtoolkit-20.11.4.data/scripts/lightroom.py
grtoolkit-20.11.4.data/scripts/nxseed.py
grtoolkit-20.11.4.data/scripts/pypackages.py
grtoolkit-20.11.4.dist-info/LICENSE
grtoolkit-20.11.4.dist-info/METADATA
grtoolkit-20.11.4.dist-info/WHEEL
grtoolkit-20.11.4.dist-info/top_level.txt
grtoolkit-20.11.4.dist-info/RECORD
