Metadata-Version: 2.1
Name: grtoolkit
Version: 20.11.4
Summary: Common functions for quick python development
Home-page: https://github.com/ZenosParadox/grtoolkit
Author: Gabriel Rosales
Author-email: gabriel.alejandro.rosales@gmail.com
License: UNKNOWN
Platform: UNKNOWN
Classifier: Programming Language :: Python :: 3
Classifier: License :: OSI Approved :: MIT License
Classifier: Operating System :: OS Independent
Requires-Dist: PyPDF2
Requires-Dist: requests
Requires-Dist: twine
Requires-Dist: wheel
Requires-Dist: pipenv
Requires-Dist: sympy
Requires-Dist: pyautogui
Requires-Dist: numpy
Requires-Dist: pandas
Requires-Dist: matplotlib
Requires-Dist: bs4
Requires-Dist: pyodbc
Requires-Dist: scipy
